TU/__init__.py
TU/test_schema.py
data_migration/__init__.py
data_migration/core.py
data_migration/edit.py
data_migration/schema_generation.py
data_migration/script_test.py
data_migration/test_generation.py
data_migration/use_case_file.py
data_migration/use_case_storage1.py
data_migration/lang/__init__.py
data_migration/lang/json.py
data_migration/migration/__init__.py
data_migration/migration/core.py
data_migration/migration/factory.py
data_migration/patch/__init__.py
data_migration/patch/core.py
data_migration/patch/lang/__init__.py
data_migration/patch/lang/json.py
data_migration/transformation/__init__.py
data_migration/transformation/core.py
data_migration-0.2.dist-info/DESCRIPTION.rst
data_migration-0.2.dist-info/METADATA
data_migration-0.2.dist-info/RECORD
data_migration-0.2.dist-info/WHEEL
data_migration-0.2.dist-info/metadata.json
data_migration-0.2.dist-info/top_level.txt
